{"created_time":1413091366,"updated_time":1452836364,"cached_at":1466282771,"published_time":1413091366,"id":88876,"uuid":"5891279521353136016","version_id":1604570,"title":"Historic Reflections 7-1","subtitle":"The itinerary, day 7, part 1 ","comments_enabled":true,"cover_media":{"id":"fake_ma_from_element_11461682","updated_at":1452836364,"created_at":1452836364,"type":"image","image":{"id":2253866,"uuid":219941640741875740,"is_processing":false,"representations":{"512":{"url":"https://d12oemfd9cl6ha.cloudfront.net/i/client_uploads/181019/5D63156C-77B6-4648-A013-66B547C8C347.jpg?w=512&h=512&crop_mode=fit&v=2","size":{"width":512,"height":341}},"1024":{"url":"https://d12oemfd9cl6ha.cloudfront.net/i/client_uploads/181019/5D63156C-77B6-4648-A013-66B547C8C347.jpg?w=1024&h=1024&crop_mode=fit&v=2","size":{"width":1024,"height":683}},"2048":{"url":"media/a9737f2e-2b6d-4385-9d26-c67f5c29ae56.jpg","size":{"width":2048,"height":1365}}},"zoom":1,"focalpoint":{"x":0.5,"y":0.5},"size":{"width":1024,"height":683},"url":"https://d12oemfd9cl6ha.cloudfront.net/i/client_uploads/181019/5D63156C-77B6-4648-A013-66B547C8C347.jpg","preprocessed_url":"https://d12oemfd9cl6ha.cloudfront.net/api2/media/client_uploads/181019/5D63156C-77B6-4648-A013-66B547C8C347.jpg","low_res_preview":null}},"favorite_count":1,"repost_count":0,"ready_version_exists":true,"published":true,"private":true,"url":"https://www.storehouse.co/stories/t6ibf-historic-reflections-7-1","short_url":"https://strh.se/LLul","slug":"t6ibf","elements":[{"id":11461683,"updated_at":1452836364,"created_at":1452836364,"content":{"id":"fake_ma_from_element_11461683","updated_at":1452836364,"created_at":1452836364,"type":"text","text":{"id":2502699,"plain_text":"Naxos & Castellomo, Sicily ","rich_text":"","text_style":"pull_quote","modifiers":[],"alignment":"left"}},"layout_type":"block","grid_size":{"width":2,"height":2},"title":null,"mute":false},{"id":11461684,"updated_at":1452836364,"created_at":1452836364,"content":{"id":"fake_ma_from_element_11461684","updated_at":1452836364,"created_at":1452836364,"type":"text","text":{"id":2502700,"plain_text":"Another peaceful moonlit night at sea transported us to Sicily gazing upon the flanks of Mt. Etna, the largest active volcano in Europe, at 10,922 feet (3,329 meters) and growing. Like most stratovolcanoes, it looms over its territory—it is simply immense at 86 miles (140km) in circumference—breathtaking in the chill morning light beneath a blanket of scudding clouds.","rich_text":"","text_style":"body","modifiers":[],"alignment":"left"}},"layout_type":"block","grid_size":{"width":2,"height":2},"title":null,"mute":false},{"id":11461685,"updated_at":1452836364,"created_at":1452836364,"content":{"id":"fake_ma_from_element_11461685","updated_at":1452836364,"created_at":1452836364,"type":"image","image":{"id":2180191,"uuid":214451221640382240,"is_processing":false,"representations":{"512":{"url":"https://d12oemfd9cl6ha.cloudfront.net/i/client_uploads/181019/08E6F0ED-38F5-4EF7-8B2B-A3042B82CB0A.jpg?w=512&h=512&crop_mode=fit&v=2","size":{"width":512,"height":341}},"1024":{"url":"https://d12oemfd9cl6ha.cloudfront.net/i/client_uploads/181019/08E6F0ED-38F5-4EF7-8B2B-A3042B82CB0A.jpg?w=1024&h=1024&crop_mode=fit&v=2","size":{"width":1024,"height":683}},"2048":{"url":"media/1ea1b091-7f5e-42b0-bf32-baa965d63a21.jpg","size":{"width":2048,"height":1365}}},"zoom":1,"focalpoint":{"x":0.5,"y":0.5},"size":{"width":1024,"height":683},"url":"https://d12oemfd9cl6ha.cloudfront.net/i/client_uploads/181019/08E6F0ED-38F5-4EF7-8B2B-A3042B82CB0A.jpg","preprocessed_url":"https://d12oemfd9cl6ha.cloudfront.net/api2/media/client_uploads/181019/08E6F0ED-38F5-4EF7-8B2B-A3042B82CB0A.jpg","low_res_preview":null}},"layout_type":"grid","grid_size":{"width":6,"height":4},"title":null,"mute":false},{"id":11461686,"updated_at":1452836364,"created_at":1452836364,"content":{"id":"fake_ma_from_element_11461686","updated_at":1452836364,"created_at":1452836364,"type":"text","text":{"id":2502701,"plain_text":"Foregoing the package excursions, we're dropped at the pier, left to improvise our own adventur beginning in truly ancient Giardini Naxos, inhabited by the Siculi even before the Greeks arrived on the Sicilian coast in 734 BC to colonize it. There we could have idled away a very pleasant day on the beach or sampling the picturesque shops and rustic eateries—but instead set our sights on the only slightly less ancient Taormina, about 4 miles north and east up a steep gradient. \n\nWalking was out of the question, so we darted over to the taxis queued up awaiting their tourist cargo, and there met the enterprising Nunzio. After brief introductions he agreed to drive us into town but immediately pitched an optional package deal—that no doubt had served many others as well as it did for us—rather than just providing a lift into town, we could engage him for the day, starting with a quick driving tour of the environs, culminating at one end of the Corso Umberto, the main street of Taormina, where we would later rendezvous for our return trip. All for the reasonable negotiated sum of $125 US.* After a few tweaks to the itinerary we agreed to his terms, and set off along the beach and up the incline to Castelmola, the little village overlooking Taormina. \n\n*Once again I'm struck by the contrast between this experience and the typical highly regulated (for your protection ;-) and inflexible taxi service in the US where our transaction would be illegal. We were so pleased with his service that he ended his day with a 40% tip.","rich_text":"","text_style":"body","modifiers":[],"alignment":"left"}},"layout_type":"block","grid_size":{"width":2,"height":2},"title":null,"mute":false},{"id":11461687,"updated_at":1452836364,"created_at":1452836364,"content":{"id":"fake_ma_from_element_11461687","updated_at":1452836364,"created_at":1452836364,"type":"image","image":{"id":2184937,"uuid":214766673182511780,"is_processing":false,"representations":{"512":{"url":"https://d12oemfd9cl6ha.cloudfront.net/i/client_uploads/181019/CD7D02D8-A8BD-4949-BB8F-E1C2CCFF8688.jpg?w=512&h=512&crop_mode=fit&v=2","size":{"width":512,"height":384}},"1024":{"url":"https://d12oemfd9cl6ha.cloudfront.net/i/client_uploads/181019/CD7D02D8-A8BD-4949-BB8F-E1C2CCFF8688.jpg?w=1024&h=1024&crop_mode=fit&v=2","size":{"width":1024,"height":768}},"2048":{"url":"media/7d7d0a49-946a-4701-91d4-94d2986a001b.jpg","size":{"width":2048,"height":1536}}},"zoom":1,"focalpoint":{"x":0.5,"y":0.3679012345679012},"size":{"width":1024,"height":768},"url":"https://d12oemfd9cl6ha.cloudfront.net/i/client_uploads/181019/CD7D02D8-A8BD-4949-BB8F-E1C2CCFF8688.jpg","preprocessed_url":"https://d12oemfd9cl6ha.cloudfront.net/api2/media/client_uploads/181019/CD7D02D8-A8BD-4949-BB8F-E1C2CCFF8688.jpg","low_res_preview":null}},"layout_type":"grid","grid_size":{"width":4,"height":2},"title":null,"mute":false},{"id":11461688,"updated_at":1452836364,"created_at":1452836364,"content":{"id":"fake_ma_from_element_11461688","updated_at":1452836364,"created_at":1452836364,"type":"image","image":{"id":2191489,"uuid":215094531146264420,"is_processing":false,"representations":{"512":{"url":"https://d12oemfd9cl6ha.cloudfront.net/i/client_uploads/181019/EA42DD0D-507A-4770-9BC3-B438C6FCA373.jpg?w=512&h=512&crop_mode=fit&v=2","size":{"width":512,"height":341}},"1024":{"url":"https://d12oemfd9cl6ha.cloudfront.net/i/client_uploads/181019/EA42DD0D-507A-4770-9BC3-B438C6FCA373.jpg?w=1024&h=1024&crop_mode=fit&v=2","size":{"width":1024,"height":683}},"2048":{"url":"media/6763a627-466a-45c4-afde-c931db0d8bd5.jpg","size":{"width":2048,"height":1365}}},"zoom":1,"focalpoint":{"x":0.3346153846153846,"y":0.5},"size":{"width":1024,"height":683},"url":"https://d12oemfd9cl6ha.cloudfront.net/i/client_uploads/181019/EA42DD0D-507A-4770-9BC3-B438C6FCA373.jpg","preprocessed_url":"https://d12oemfd9cl6ha.cloudfront.net/api2/media/client_uploads/181019/EA42DD0D-507A-4770-9BC3-B438C6FCA373.jpg","low_res_preview":null}},"layout_type":"grid","grid_size":{"width":2,"height":2},"title":null,"mute":false},{"id":11461689,"updated_at":1452836364,"created_at":1452836364,"content":{"id":"fake_ma_from_element_11461689","updated_at":1452836364,"created_at":1452836364,"type":"image","image":{"id":2191491,"uuid":215094554454960200,"is_processing":false,"representations":{"512":{"url":"https://d12oemfd9cl6ha.cloudfront.net/i/client_uploads/181019/2E7817DE-9683-436C-94DF-28FBAD1B3E76.jpg?w=512&h=512&crop_mode=fit&v=2","size":{"width":512,"height":194}},"1024":{"url":"https://d12oemfd9cl6ha.cloudfront.net/i/client_uploads/181019/2E7817DE-9683-436C-94DF-28FBAD1B3E76.jpg?w=1024&h=1024&crop_mode=fit&v=2","size":{"width":1024,"height":389}},"2048":{"url":"media/43eb483c-45bf-4860-8be1-601ac92e54b1.jpg","size":{"width":2048,"height":778}}},"zoom":1,"focalpoint":{"x":0.3891789273849074,"y":0.5},"size":{"width":1024,"height":389},"url":"https://d12oemfd9cl6ha.cloudfront.net/i/client_uploads/181019/2E7817DE-9683-436C-94DF-28FBAD1B3E76.jpg","preprocessed_url":"https://d12oemfd9cl6ha.cloudfront.net/api2/media/client_uploads/181019/2E7817DE-9683-436C-94DF-28FBAD1B3E76.jpg","low_res_preview":null}},"layout_type":"grid","grid_size":{"width":6,"height":3},"title":null,"mute":false},{"id":11461690,"updated_at":1452836364,"created_at":1452836364,"content":{"id":"fake_ma_from_element_11461690","updated_at":1452836364,"created_at":1452836364,"type":"image","image":{"id":2191492,"uuid":215094566010638940,"is_processing":false,"representations":{"512":{"url":"https://d12oemfd9cl6ha.cloudfront.net/i/client_uploads/181019/0618B022-6952-4976-A7A1-AC8BAE58823A.jpg?w=512&h=512&crop_mode=fit&v=2","size":{"width":512,"height":288}},"1024":{"url":"https://d12oemfd9cl6ha.cloudfront.net/i/client_uploads/181019/0618B022-6952-4976-A7A1-AC8BAE58823A.jpg?w=1024&h=1024&crop_mode=fit&v=2","size":{"width":1024,"height":576}},"2048":{"url":"media/733da7da-0a54-4ed2-a439-c63d64a801c6.jpg","size":{"width":2048,"height":1152}}},"zoom":1,"focalpoint":{"x":0.5,"y":0.6268980477223427},"size":{"width":1024,"height":576},"url":"https://d12oemfd9cl6ha.cloudfront.net/i/client_uploads/181019/0618B022-6952-4976-A7A1-AC8BAE58823A.jpg","preprocessed_url":"https://d12oemfd9cl6ha.cloudfront.net/api2/media/client_uploads/181019/0618B022-6952-4976-A7A1-AC8BAE58823A.jpg","low_res_preview":null}},"layout_type":"grid","grid_size":{"width":6,"height":2},"title":null,"mute":false},{"id":11461691,"updated_at":1452836364,"created_at":1452836364,"content":{"id":"fake_ma_from_element_11461691","updated_at":1452836364,"created_at":1452836364,"type":"image","image":{"id":2180190,"uuid":214451214865107500,"is_processing":false,"representations":{"512":{"url":"https://d12oemfd9cl6ha.cloudfront.net/i/client_uploads/181019/7DB64E24-2953-45F8-85BB-3609A4A80763.jpg?w=512&h=512&crop_mode=fit&v=2","size":{"width":512,"height":341}},"1024":{"url":"https://d12oemfd9cl6ha.cloudfront.net/i/client_uploads/181019/7DB64E24-2953-45F8-85BB-3609A4A80763.jpg?w=1024&h=1024&crop_mode=fit&v=2","size":{"width":1024,"height":683}},"2048":{"url":"media/6ee294ad-95c7-42bb-b42e-9abbe86dcbaf.jpg","size":{"width":2048,"height":1365}}},"zoom":1,"focalpoint":{"x":0.5,"y":0.5},"size":{"width":1024,"height":683},"url":"https://d12oemfd9cl6ha.cloudfront.net/i/client_uploads/181019/7DB64E24-2953-45F8-85BB-3609A4A80763.jpg","preprocessed_url":"https://d12oemfd9cl6ha.cloudfront.net/api2/media/client_uploads/181019/7DB64E24-2953-45F8-85BB-3609A4A80763.jpg","low_res_preview":null}},"layout_type":"grid","grid_size":{"width":4,"height":3},"title":null,"mute":false},{"id":11461692,"updated_at":1452836364,"created_at":1452836364,"content":{"id":"fake_ma_from_element_11461692","updated_at":1452836364,"created_at":1452836364,"type":"image","image":{"id":2180189,"uuid":214451207221255500,"is_processing":false,"representations":{"512":{"url":"https://d12oemfd9cl6ha.cloudfront.net/i/client_uploads/181019/38DE71E0-AACC-4BD8-95C4-262400BBBB7D.jpg?w=512&h=512&crop_mode=fit&v=2","size":{"width":512,"height":341}},"1024":{"url":"https://d12oemfd9cl6ha.cloudfront.net/i/client_uploads/181019/38DE71E0-AACC-4BD8-95C4-262400BBBB7D.jpg?w=1024&h=1024&crop_mode=fit&v=2","size":{"width":1024,"height":683}},"2048":{"url":"media/0c308244-97cf-4e7d-81f8-6b66c1dd64e4.jpg","size":{"width":2048,"height":1365}}},"zoom":1,"focalpoint":{"x":0.5308333333333334,"y":0.5},"size":{"width":1024,"height":683},"url":"https://d12oemfd9cl6ha.cloudfront.net/i/client_uploads/181019/38DE71E0-AACC-4BD8-95C4-262400BBBB7D.jpg","preprocessed_url":"https://d12oemfd9cl6ha.cloudfront.net/api2/media/client_uploads/181019/38DE71E0-AACC-4BD8-95C4-262400BBBB7D.jpg","low_res_preview":null}},"layout_type":"grid","grid_size":{"width":2,"height":3},"title":null,"mute":false},{"id":11461693,"updated_at":1452836364,"created_at":1452836364,"content":{"id":"fake_ma_from_element_11461693","updated_at":1452836364,"created_at":1452836364,"type":"image","image":{"id":2184934,"uuid":214766646107098800,"is_processing":false,"representations":{"512":{"url":"https://d12oemfd9cl6ha.cloudfront.net/i/client_uploads/181019/62B6174B-113E-4C16-B3CE-05871A3B7529.jpg?w=512&h=512&crop_mode=fit&v=2","size":{"width":512,"height":341}},"1024":{"url":"https://d12oemfd9cl6ha.cloudfront.net/i/client_uploads/181019/62B6174B-113E-4C16-B3CE-05871A3B7529.jpg?w=1024&h=1024&crop_mode=fit&v=2","size":{"width":1024,"height":683}},"2048":{"url":"media/509e36f0-24ed-40ce-9ffe-0d0d72812653.jpg","size":{"width":2048,"height":1365}}},"zoom":2.464499235153198,"focalpoint":{"x":0.5623761573900194,"y":0.7162687970277635},"size":{"width":1024,"height":683},"url":"https://d12oemfd9cl6ha.cloudfront.net/i/client_uploads/181019/62B6174B-113E-4C16-B3CE-05871A3B7529.jpg","preprocessed_url":"https://d12oemfd9cl6ha.cloudfront.net/api2/media/client_uploads/181019/62B6174B-113E-4C16-B3CE-05871A3B7529.jpg","low_res_preview":null}},"layout_type":"grid","grid_size":{"width":6,"height":2},"title":null,"mute":false},{"id":11461694,"updated_at":1452836364,"created_at":1452836364,"content":{"id":"fake_ma_from_element_11461694","updated_at":1452836364,"created_at":1452836364,"type":"image","image":{"id":2191494,"uuid":215094646146354620,"is_processing":false,"representations":{"512":{"url":"https://d12oemfd9cl6ha.cloudfront.net/i/client_uploads/181019/F9593232-3558-4A9F-86C6-4D8877414239.jpg?w=512&h=512&crop_mode=fit&v=2","size":{"width":512,"height":76}},"1024":{"url":"https://d12oemfd9cl6ha.cloudfront.net/i/client_uploads/181019/F9593232-3558-4A9F-86C6-4D8877414239.jpg?w=1024&h=1024&crop_mode=fit&v=2","size":{"width":1024,"height":152}},"2048":{"url":"media/7b3b2c58-3b59-4d6b-bb04-68294c53d039.jpg","size":{"width":2048,"height":304}}},"zoom":1,"focalpoint":{"x":0.5,"y":0.5},"size":{"width":1024,"height":152},"url":"https://d12oemfd9cl6ha.cloudfront.net/i/client_uploads/181019/F9593232-3558-4A9F-86C6-4D8877414239.jpg","preprocessed_url":"https://d12oemfd9cl6ha.cloudfront.net/api2/media/client_uploads/181019/F9593232-3558-4A9F-86C6-4D8877414239.jpg","low_res_preview":null}},"layout_type":"grid","grid_size":{"width":6,"height":2},"title":null,"mute":false},{"id":11461695,"updated_at":1452836364,"created_at":1452836364,"content":{"id":"fake_ma_from_element_11461695","updated_at":1452836364,"created_at":1452836364,"type":"text","text":{"id":2502702,"plain_text":"Nunzio turns out to be an entertaining tour guide and storyteller—we learn a lot about the local history and economy, politics, site specific information, fascists, the mafioso, and recent events (more on that later) as he took us to each new vista. He stopped whenever and wherever we wanted and patiently waited for my prolific photos, frequently stepping in to do a decent job taking portraits of the four of us. \n\nAfter several switchbacks no tour bus could negotiate (even scooters had to be cautious) we arrived at a little shrine and a ruined castle (one of two for which the town is named). It was then we could see evidence of the recent eruption Nunzio told us of—coarse black ash was deposited everywhere, most evident between the rough paving stones underfoot.","rich_text":"","text_style":"body","modifiers":[],"alignment":"left"}},"layout_type":"block","grid_size":{"width":2,"height":2},"title":null,"mute":false},{"id":11461696,"updated_at":1452836364,"created_at":1452836364,"content":{"id":"fake_ma_from_element_11461696","updated_at":1452836364,"created_at":1452836364,"type":"image","image":{"id":2257100,"uuid":220102073047543520,"is_processing":false,"representations":{"512":{"url":"https://d12oemfd9cl6ha.cloudfront.net/i/client_uploads/181019/4AB8F805-0ADD-4A6F-ACC6-B08BB7FA44AF.jpg?w=512&h=512&crop_mode=fit&v=2","size":{"width":512,"height":341}},"1024":{"url":"https://d12oemfd9cl6ha.cloudfront.net/i/client_uploads/181019/4AB8F805-0ADD-4A6F-ACC6-B08BB7FA44AF.jpg?w=1024&h=1024&crop_mode=fit&v=2","size":{"width":1024,"height":683}},"2048":{"url":"media/ee606334-d1b3-4adf-99da-6f415c047f42.jpg","size":{"width":2048,"height":1365}}},"zoom":1,"focalpoint":{"x":0.5,"y":0.42451967063129},"size":{"width":1024,"height":683},"url":"https://d12oemfd9cl6ha.cloudfront.net/i/client_uploads/181019/4AB8F805-0ADD-4A6F-ACC6-B08BB7FA44AF.jpg","preprocessed_url":"https://d12oemfd9cl6ha.cloudfront.net/api2/media/client_uploads/181019/4AB8F805-0ADD-4A6F-ACC6-B08BB7FA44AF.jpg","low_res_preview":null}},"layout_type":"grid","grid_size":{"width":6,"height":3},"title":null,"mute":false},{"id":11461697,"updated_at":1452836364,"created_at":1452836364,"content":{"id":"fake_ma_from_element_11461697","updated_at":1452836364,"created_at":1452836364,"type":"text","text":{"id":2502703,"plain_text":"There isn't much to Castellomo but it is definitely worth the visit. Situated on the top of Mount Tauro, the Santuario Madonna della Rocca (Sanctuary of the Madonna of the Rock) shrine offers a sweeping panorama of Taormina on the narrow plateau directly below, the beautiful coastline below that, and of Mt. Etna beyond—simply breathtaking. \n\nDescending precipitously off the edge of the cliff, a cobble–paved path called the Salita Castello plunges down to Taormina—three of us enthusiastically endorse trekking down it if we had more time, the fourth threatening mutiny if we dared (NancyEllen grew dizzy just looking at it). ","rich_text":"","text_style":"body","modifiers":[],"alignment":"left"}},"layout_type":"block","grid_size":{"width":2,"height":2},"title":null,"mute":false},{"id":11461698,"updated_at":1452836364,"created_at":1452836364,"content":{"id":"fake_ma_from_element_11461698","updated_at":1452836364,"created_at":1452836364,"type":"image","image":{"id":2257004,"uuid":220096998032986400,"is_processing":false,"representations":{"512":{"url":"https://d12oemfd9cl6ha.cloudfront.net/i/client_uploads/181019/5C69BE6B-4B28-4D27-AC7C-E9C86694A5DE.jpg?w=512&h=512&crop_mode=fit&v=2","size":{"width":512,"height":341}},"1024":{"url":"https://d12oemfd9cl6ha.cloudfront.net/i/client_uploads/181019/5C69BE6B-4B28-4D27-AC7C-E9C86694A5DE.jpg?w=1024&h=1024&crop_mode=fit&v=2","size":{"width":1024,"height":683}},"2048":{"url":"media/6bd8f214-bfd1-422a-9276-cfeb914e9ea9.jpg","size":{"width":2048,"height":1365}}},"zoom":1,"focalpoint":{"x":0.5,"y":0.5},"size":{"width":1024,"height":683},"url":"https://d12oemfd9cl6ha.cloudfront.net/i/client_uploads/181019/5C69BE6B-4B28-4D27-AC7C-E9C86694A5DE.jpg","preprocessed_url":"https://d12oemfd9cl6ha.cloudfront.net/api2/media/client_uploads/181019/5C69BE6B-4B28-4D27-AC7C-E9C86694A5DE.jpg","low_res_preview":null}},"layout_type":"grid","grid_size":{"width":6,"height":4},"title":null,"mute":false},{"id":11461699,"updated_at":1452836364,"created_at":1452836364,"content":{"id":"fake_ma_from_element_11461699","updated_at":1452836364,"created_at":1452836364,"type":"image","image":{"id":2180201,"uuid":214451363036913060,"is_processing":false,"representations":{"512":{"url":"https://d12oemfd9cl6ha.cloudfront.net/i/client_uploads/181019/2AB8DCCB-1F80-49D1-B1B3-84B245ED07F7.jpg?w=512&h=512&crop_mode=fit&v=2","size":{"width":512,"height":341}},"1024":{"url":"https://d12oemfd9cl6ha.cloudfront.net/i/client_uploads/181019/2AB8DCCB-1F80-49D1-B1B3-84B245ED07F7.jpg?w=1024&h=1024&crop_mode=fit&v=2","size":{"width":1024,"height":683}},"2048":{"url":"media/72e0cc75-b0d0-483d-b8cd-9917c5ec09db.jpg","size":{"width":2048,"height":1365}}},"zoom":1,"focalpoint":{"x":0.5,"y":0.505946935041171},"size":{"width":1024,"height":683},"url":"https://d12oemfd9cl6ha.cloudfront.net/i/client_uploads/181019/2AB8DCCB-1F80-49D1-B1B3-84B245ED07F7.jpg","preprocessed_url":"https://d12oemfd9cl6ha.cloudfront.net/api2/media/client_uploads/181019/2AB8DCCB-1F80-49D1-B1B3-84B245ED07F7.jpg","low_res_preview":null}},"layout_type":"grid","grid_size":{"width":6,"height":4},"title":null,"mute":false},{"id":11461700,"updated_at":1452836364,"created_at":1452836364,"content":{"id":"fake_ma_from_element_11461700","updated_at":1452836364,"created_at":1452836364,"type":"image","image":{"id":2180200,"uuid":214451352368557300,"is_processing":false,"representations":{"512":{"url":"https://d12oemfd9cl6ha.cloudfront.net/i/client_uploads/181019/0C1F477E-ACFC-4A73-97F1-3AB15903B939.jpg?w=512&h=512&crop_mode=fit&v=2","size":{"width":512,"height":341}},"1024":{"url":"https://d12oemfd9cl6ha.cloudfront.net/i/client_uploads/181019/0C1F477E-ACFC-4A73-97F1-3AB15903B939.jpg?w=1024&h=1024&crop_mode=fit&v=2","size":{"width":1024,"height":683}},"2048":{"url":"media/610edcfc-02ff-41a0-85f5-31f03aaa9f03.jpg","size":{"width":2048,"height":1365}}},"zoom":1,"focalpoint":{"x":0.5,"y":0.5},"size":{"width":1024,"height":683},"url":"https://d12oemfd9cl6ha.cloudfront.net/i/client_uploads/181019/0C1F477E-ACFC-4A73-97F1-3AB15903B939.jpg","preprocessed_url":"https://d12oemfd9cl6ha.cloudfront.net/api2/media/client_uploads/181019/0C1F477E-ACFC-4A73-97F1-3AB15903B939.jpg","low_res_preview":null}},"layout_type":"grid","grid_size":{"width":6,"height":4},"title":null,"mute":false},{"id":11461701,"updated_at":1452836364,"created_at":1452836364,"content":{"id":"fake_ma_from_element_11461701","updated_at":1452836364,"created_at":1452836364,"type":"image","image":{"id":2257050,"uuid":220100453785315000,"is_processing":false,"representations":{"512":{"url":"https://d12oemfd9cl6ha.cloudfront.net/i/client_uploads/181019/5719895F-0463-4018-8038-287C2902FC4B.jpg?w=512&h=512&crop_mode=fit&v=2","size":{"width":512,"height":341}},"1024":{"url":"https://d12oemfd9cl6ha.cloudfront.net/i/client_uploads/181019/5719895F-0463-4018-8038-287C2902FC4B.jpg?w=1024&h=1024&crop_mode=fit&v=2","size":{"width":1024,"height":683}},"2048":{"url":"media/a4c892c3-e136-4d36-98ed-c277df4a8e88.jpg","size":{"width":2048,"height":1365}}},"zoom":1,"focalpoint":{"x":0.5,"y":0.3815187557182068},"size":{"width":1024,"height":683},"url":"https://d12oemfd9cl6ha.cloudfront.net/i/client_uploads/181019/5719895F-0463-4018-8038-287C2902FC4B.jpg","preprocessed_url":"https://d12oemfd9cl6ha.cloudfront.net/api2/media/client_uploads/181019/5719895F-0463-4018-8038-287C2902FC4B.jpg","low_res_preview":null}},"layout_type":"grid","grid_size":{"width":6,"height":3},"title":null,"mute":false},{"id":11461702,"updated_at":1452836364,"created_at":1452836364,"content":{"id":"fake_ma_from_element_11461702","updated_at":1452836364,"created_at":1452836364,"type":"text","text":{"id":2502704,"plain_text":"The namesake Saracen castle at the summit was a closed archeological site at the time of our visit so we turned our attention back to the sanctuary that was, externally at least, nondescript. Inside the shrine is hewn from a natural rocky grotto making for an unusual juxtaposition of fine smoothly carved marble and craggy volcanic outcrops.  ","rich_text":"","text_style":"body","modifiers":[],"alignment":"left"}},"layout_type":"block","grid_size":{"width":2,"height":2},"title":null,"mute":false},{"id":11461703,"updated_at":1452836364,"created_at":1452836364,"content":{"id":"fake_ma_from_element_11461703","updated_at":1452836364,"created_at":1452836364,"type":"image","image":{"id":2240402,"uuid":219118767736832000,"is_processing":false,"representations":{"512":{"url":"https://d12oemfd9cl6ha.cloudfront.net/i/client_uploads/181019/4317FA47-5736-48EE-B389-E94E7AAD890F.jpg?w=512&h=512&crop_mode=fit&v=2","size":{"width":512,"height":341}},"1024":{"url":"https://d12oemfd9cl6ha.cloudfront.net/i/client_uploads/181019/4317FA47-5736-48EE-B389-E94E7AAD890F.jpg?w=1024&h=1024&crop_mode=fit&v=2","size":{"width":1024,"height":683}},"2048":{"url":"media/ec76672d-0a04-40ac-9ce1-a478e0ff3ea2.jpg","size":{"width":2048,"height":1365}}},"zoom":1,"focalpoint":{"x":0.5,"y":0.5},"size":{"width":1024,"height":683},"url":"https://d12oemfd9cl6ha.cloudfront.net/i/client_uploads/181019/4317FA47-5736-48EE-B389-E94E7AAD890F.jpg","preprocessed_url":"https://d12oemfd9cl6ha.cloudfront.net/api2/media/client_uploads/181019/4317FA47-5736-48EE-B389-E94E7AAD890F.jpg","low_res_preview":null}},"layout_type":"grid","grid_size":{"width":6,"height":4},"title":null,"mute":false},{"id":11461704,"updated_at":1452836364,"created_at":1452836364,"content":{"id":"fake_ma_from_element_11461704","updated_at":1452836364,"created_at":1452836364,"type":"image","image":{"id":2191487,"uuid":215094509565806180,"is_processing":false,"representations":{"512":{"url":"https://d12oemfd9cl6ha.cloudfront.net/i/client_uploads/181019/290A0E12-AB99-43A8-A8AD-A8425CBCFD2B.jpg?w=512&h=512&crop_mode=fit&v=2","size":{"width":512,"height":341}},"1024":{"url":"https://d12oemfd9cl6ha.cloudfront.net/i/client_uploads/181019/290A0E12-AB99-43A8-A8AD-A8425CBCFD2B.jpg?w=1024&h=1024&crop_mode=fit&v=2","size":{"width":1024,"height":683}},"2048":{"url":"media/d8ab1b0f-6e96-488a-841f-3c30c9473111.jpg","size":{"width":2048,"height":1365}}},"zoom":1,"focalpoint":{"x":0.5,"y":0.5},"size":{"width":1024,"height":683},"url":"https://d12oemfd9cl6ha.cloudfront.net/i/client_uploads/181019/290A0E12-AB99-43A8-A8AD-A8425CBCFD2B.jpg","preprocessed_url":"https://d12oemfd9cl6ha.cloudfront.net/api2/media/client_uploads/181019/290A0E12-AB99-43A8-A8AD-A8425CBCFD2B.jpg","low_res_preview":null}},"layout_type":"grid","grid_size":{"width":3,"height":2},"title":null,"mute":false},{"id":11461705,"updated_at":1452836364,"created_at":1452836364,"content":{"id":"fake_ma_from_element_11461705","updated_at":1452836364,"created_at":1452836364,"type":"image","image":{"id":2191490,"uuid":215094539709888400,"is_processing":false,"representations":{"512":{"url":"https://d12oemfd9cl6ha.cloudfront.net/i/client_uploads/181019/5F86467D-FFB8-4801-9170-1370D2128785.jpg?w=512&h=512&crop_mode=fit&v=2","size":{"width":512,"height":341}},"1024":{"url":"https://d12oemfd9cl6ha.cloudfront.net/i/client_uploads/181019/5F86467D-FFB8-4801-9170-1370D2128785.jpg?w=1024&h=1024&crop_mode=fit&v=2","size":{"width":1024,"height":683}},"2048":{"url":"media/dd300d4a-bcfd-4596-a4a4-a8a766b4f232.jpg","size":{"width":2048,"height":1365}}},"zoom":1,"focalpoint":{"x":0.6666666666666666,"y":0.5},"size":{"width":1024,"height":683},"url":"https://d12oemfd9cl6ha.cloudfront.net/i/client_uploads/181019/5F86467D-FFB8-4801-9170-1370D2128785.jpg","preprocessed_url":"https://d12oemfd9cl6ha.cloudfront.net/api2/media/client_uploads/181019/5F86467D-FFB8-4801-9170-1370D2128785.jpg","low_res_preview":null}},"layout_type":"grid","grid_size":{"width":3,"height":2},"title":null,"mute":false},{"id":11461706,"updated_at":1452836364,"created_at":1452836364,"content":{"id":"fake_ma_from_element_11461706","updated_at":1452836364,"created_at":1452836364,"type":"image","image":{"id":2180222,"uuid":214451512359040130,"is_processing":false,"representations":{"512":{"url":"https://d12oemfd9cl6ha.cloudfront.net/i/client_uploads/181019/55894E58-35F6-4B36-A8F3-3A8F0051AC87.jpg?w=512&h=512&crop_mode=fit&v=2","size":{"width":512,"height":341}},"1024":{"url":"https://d12oemfd9cl6ha.cloudfront.net/i/client_uploads/181019/55894E58-35F6-4B36-A8F3-3A8F0051AC87.jpg?w=1024&h=1024&crop_mode=fit&v=2","size":{"width":1024,"height":683}},"2048":{"url":"media/77ac5871-ff02-4ece-8cdc-a24694789b88.jpg","size":{"width":2048,"height":1365}}},"zoom":1,"focalpoint":{"x":0.5747967479674797,"y":0.5},"size":{"width":1024,"height":683},"url":"https://d12oemfd9cl6ha.cloudfront.net/i/client_uploads/181019/55894E58-35F6-4B36-A8F3-3A8F0051AC87.jpg","preprocessed_url":"https://d12oemfd9cl6ha.cloudfront.net/api2/media/client_uploads/181019/55894E58-35F6-4B36-A8F3-3A8F0051AC87.jpg","low_res_preview":null}},"layout_type":"grid","grid_size":{"width":6,"height":6},"title":null,"mute":false},{"id":11461707,"updated_at":1452836364,"created_at":1452836364,"content":{"id":"fake_ma_from_element_11461707","updated_at":1452836364,"created_at":1452836364,"type":"text","text":{"id":2502705,"plain_text":"Dropping across a small saddle of connecting ridge, we rounded another tight turn into the main square—a space so authentically Sicilian in appearance that it strikes American eyes as a movie set, it's just too perfect. Costumed villagers, wearing exactly what you would picture Sicilian's wearing, languidly spill out of church onto the cobblestone square looking as if they are going to break into a Sicilian dance for the festival scheduled later in the day. Merchants and farmers peddle their wares at the margins as children scurry about. The sun sparkles on the sea below, the gentle breeze carrying the aroma wafting from an unseen kitchen. It is a moment we won't forget and that we would never have known to seek out, but for Nunzio.","rich_text":"","text_style":"body","modifiers":[],"alignment":"left"}},"layout_type":"block","grid_size":{"width":2,"height":2},"title":null,"mute":false},{"id":11461708,"updated_at":1452836364,"created_at":1452836364,"content":{"id":"fake_ma_from_element_11461708","updated_at":1452836364,"created_at":1452836364,"type":"image","image":{"id":2242053,"uuid":219202533918427040,"is_processing":false,"representations":{"512":{"url":"https://d12oemfd9cl6ha.cloudfront.net/i/client_uploads/181019/48ED9E48-4F58-4AC7-A549-E638107767E6.jpg?w=512&h=512&crop_mode=fit&v=2","size":{"width":512,"height":341}},"1024":{"url":"https://d12oemfd9cl6ha.cloudfront.net/i/client_uploads/181019/48ED9E48-4F58-4AC7-A549-E638107767E6.jpg?w=1024&h=1024&crop_mode=fit&v=2","size":{"width":1024,"height":683}},"2048":{"url":"media/e8615a88-bc24-4510-82fd-a6490112ce05.jpg","size":{"width":2048,"height":1365}}},"zoom":1.316365361213684,"focalpoint":{"x":0.4789611029476098,"y":0.4747053171436278},"size":{"width":1024,"height":683},"url":"https://d12oemfd9cl6ha.cloudfront.net/i/client_uploads/181019/48ED9E48-4F58-4AC7-A549-E638107767E6.jpg","preprocessed_url":"https://d12oemfd9cl6ha.cloudfront.net/api2/media/client_uploads/181019/48ED9E48-4F58-4AC7-A549-E638107767E6.jpg","low_res_preview":null}},"layout_type":"grid","grid_size":{"width":6,"height":3},"title":null,"mute":false},{"id":11461709,"updated_at":1452836364,"created_at":1452836364,"content":{"id":"fake_ma_from_element_11461709","updated_at":1452836364,"created_at":1452836364,"type":"image","image":{"id":2259382,"uuid":220224336442891870,"is_processing":false,"representations":{"512":{"url":"https://d12oemfd9cl6ha.cloudfront.net/i/client_uploads/181019/F5B7FE0F-D6D5-4A55-B66D-93F5145CCC9B.jpg?w=512&h=512&crop_mode=fit&v=2","size":{"width":512,"height":341}},"1024":{"url":"https://d12oemfd9cl6ha.cloudfront.net/i/client_uploads/181019/F5B7FE0F-D6D5-4A55-B66D-93F5145CCC9B.jpg?w=1024&h=1024&crop_mode=fit&v=2","size":{"width":1024,"height":683}},"2048":{"url":"media/80bb32ff-4a0b-41a6-ad66-05f8163bc790.jpg","size":{"width":2048,"height":1366}}},"zoom":1,"focalpoint":{"x":0.5,"y":0.5013723696248856},"size":{"width":1024,"height":683},"url":"https://d12oemfd9cl6ha.cloudfront.net/i/client_uploads/181019/F5B7FE0F-D6D5-4A55-B66D-93F5145CCC9B.jpg","preprocessed_url":"https://d12oemfd9cl6ha.cloudfront.net/api2/media/client_uploads/181019/F5B7FE0F-D6D5-4A55-B66D-93F5145CCC9B.jpg","low_res_preview":null}},"layout_type":"grid","grid_size":{"width":6,"height":4},"title":null,"mute":false},{"id":11461710,"updated_at":1452836364,"created_at":1452836364,"content":{"id":"fake_ma_from_element_11461710","updated_at":1452836364,"created_at":1452836364,"type":"image","image":{"id":2242054,"uuid":219202543075168160,"is_processing":false,"representations":{"512":{"url":"https://d12oemfd9cl6ha.cloudfront.net/i/client_uploads/181019/3D9297BB-88A8-43E6-B2EF-96AE532E93F1.jpg?w=512&h=512&crop_mode=fit&v=2","size":{"width":341,"height":512}},"1024":{"url":"https://d12oemfd9cl6ha.cloudfront.net/i/client_uploads/181019/3D9297BB-88A8-43E6-B2EF-96AE532E93F1.jpg?w=1024&h=1024&crop_mode=fit&v=2","size":{"width":683,"height":1024}},"2048":{"url":"media/0ae0e6bb-d4fa-485a-b6f7-486258393470.jpg","size":{"width":1365,"height":2048}}},"zoom":1,"focalpoint":{"x":0.5,"y":0.5},"size":{"width":683,"height":1024},"url":"https://d12oemfd9cl6ha.cloudfront.net/i/client_uploads/181019/3D9297BB-88A8-43E6-B2EF-96AE532E93F1.jpg","preprocessed_url":"https://d12oemfd9cl6ha.cloudfront.net/api2/media/client_uploads/181019/3D9297BB-88A8-43E6-B2EF-96AE532E93F1.jpg","low_res_preview":null}},"layout_type":"grid","grid_size":{"width":2,"height":3},"title":null,"mute":false},{"id":11461711,"updated_at":1452836364,"created_at":1452836364,"content":{"id":"fake_ma_from_element_11461711","updated_at":1452836364,"created_at":1452836364,"type":"image","image":{"id":2180221,"uuid":214451504754426530,"is_processing":false,"representations":{"512":{"url":"https://d12oemfd9cl6ha.cloudfront.net/i/client_uploads/181019/B45EB057-F69D-4DAD-B6B9-265112380A6C.jpg?w=512&h=512&crop_mode=fit&v=2","size":{"width":512,"height":341}},"1024":{"url":"https://d12oemfd9cl6ha.cloudfront.net/i/client_uploads/181019/B45EB057-F69D-4DAD-B6B9-265112380A6C.jpg?w=1024&h=1024&crop_mode=fit&v=2","size":{"width":1024,"height":683}},"2048":{"url":"media/c1625721-868a-4653-a668-d81923107384.jpg","size":{"width":2048,"height":1365}}},"zoom":1.48448657989502,"focalpoint":{"x":0.5939202641172884,"y":0.6062702128985553},"size":{"width":1024,"height":683},"url":"https://d12oemfd9cl6ha.cloudfront.net/i/client_uploads/181019/B45EB057-F69D-4DAD-B6B9-265112380A6C.jpg","preprocessed_url":"https://d12oemfd9cl6ha.cloudfront.net/api2/media/client_uploads/181019/B45EB057-F69D-4DAD-B6B9-265112380A6C.jpg","low_res_preview":null}},"layout_type":"grid","grid_size":{"width":4,"height":3},"title":null,"mute":false},{"id":11461712,"updated_at":1452836364,"created_at":1452836364,"content":{"id":"fake_ma_from_element_11461712","updated_at":1452836364,"created_at":1452836364,"type":"text","text":{"id":2502706,"plain_text":"Exploring on foot for a prearranged thirty minutes, we struck off through town seeking out the Castello (also closed on Sunday) soaking in the flavor of the place along the way.","rich_text":"","text_style":"body","modifiers":[],"alignment":"left"}},"layout_type":"block","grid_size":{"width":2,"height":2},"title":null,"mute":false},{"id":11461713,"updated_at":1452836364,"created_at":1452836364,"content":{"id":"fake_ma_from_element_11461713","updated_at":1452836364,"created_at":1452836364,"type":"image","image":{"id":2242050,"uuid":219202507905505470,"is_processing":false,"representations":{"512":{"url":"https://d12oemfd9cl6ha.cloudfront.net/i/client_uploads/181019/3F962D78-B5CD-4E51-B333-99E77094BCB3.jpg?w=512&h=512&crop_mode=fit&v=2","size":{"width":512,"height":341}},"1024":{"url":"https://d12oemfd9cl6ha.cloudfront.net/i/client_uploads/181019/3F962D78-B5CD-4E51-B333-99E77094BCB3.jpg?w=1024&h=1024&crop_mode=fit&v=2","size":{"width":1024,"height":683}},"2048":{"url":"media/490b405a-c35b-4088-baf0-fc173ed77473.jpg","size":{"width":2048,"height":1365}}},"zoom":1.232848644256592,"focalpoint":{"x":0.4109723199845881,"y":0.5596794094526956},"size":{"width":1024,"height":683},"url":"https://d12oemfd9cl6ha.cloudfront.net/i/client_uploads/181019/3F962D78-B5CD-4E51-B333-99E77094BCB3.jpg","preprocessed_url":"https://d12oemfd9cl6ha.cloudfront.net/api2/media/client_uploads/181019/3F962D78-B5CD-4E51-B333-99E77094BCB3.jpg","low_res_preview":null}},"layout_type":"grid","grid_size":{"width":4,"height":3},"title":null,"mute":false},{"id":11461714,"updated_at":1452836364,"created_at":1452836364,"content":{"id":"fake_ma_from_element_11461714","updated_at":1452836364,"created_at":1452836364,"type":"image","image":{"id":2242051,"uuid":219202516591867800,"is_processing":false,"representations":{"512":{"url":"https://d12oemfd9cl6ha.cloudfront.net/i/client_uploads/181019/DF9DD26B-1077-48E6-8707-94E058ED51CD.jpg?w=512&h=512&crop_mode=fit&v=2","size":{"width":512,"height":341}},"1024":{"url":"https://d12oemfd9cl6ha.cloudfront.net/i/client_uploads/181019/DF9DD26B-1077-48E6-8707-94E058ED51CD.jpg?w=1024&h=1024&crop_mode=fit&v=2","size":{"width":1024,"height":683}},"2048":{"url":"media/66b1fe5d-8895-44ec-ab79-d33ed7c58593.jpg","size":{"width":2048,"height":1365}}},"zoom":1,"focalpoint":{"x":0.4897058823529412,"y":0.5},"size":{"width":1024,"height":683},"url":"https://d12oemfd9cl6ha.cloudfront.net/i/client_uploads/181019/DF9DD26B-1077-48E6-8707-94E058ED51CD.jpg","preprocessed_url":"https://d12oemfd9cl6ha.cloudfront.net/api2/media/client_uploads/181019/DF9DD26B-1077-48E6-8707-94E058ED51CD.jpg","low_res_preview":null}},"layout_type":"grid","grid_size":{"width":2,"height":5},"title":null,"mute":false},{"id":11461715,"updated_at":1452836364,"created_at":1452836364,"content":{"id":"fake_ma_from_element_11461715","updated_at":1452836364,"created_at":1452836364,"type":"image","image":{"id":2242113,"uuid":219207641228221250,"is_processing":false,"representations":{"512":{"url":"https://d12oemfd9cl6ha.cloudfront.net/i/client_uploads/181019/08BCFDC8-B421-458F-BCE7-AE272E705E68.jpg?w=512&h=512&crop_mode=fit&v=2","size":{"width":512,"height":341}},"1024":{"url":"https://d12oemfd9cl6ha.cloudfront.net/i/client_uploads/181019/08BCFDC8-B421-458F-BCE7-AE272E705E68.jpg?w=1024&h=1024&crop_mode=fit&v=2","size":{"width":1024,"height":683}},"2048":{"url":"media/3d544bc2-37bc-417d-8f72-81f7c6c6f2cc.jpg","size":{"width":2048,"height":1365}}},"zoom":1,"focalpoint":{"x":0.5,"y":0.5},"size":{"width":1024,"height":683},"url":"https://d12oemfd9cl6ha.cloudfront.net/i/client_uploads/181019/08BCFDC8-B421-458F-BCE7-AE272E705E68.jpg","preprocessed_url":"https://d12oemfd9cl6ha.cloudfront.net/api2/media/client_uploads/181019/08BCFDC8-B421-458F-BCE7-AE272E705E68.jpg","low_res_preview":null}},"layout_type":"grid","grid_size":{"width":4,"height":2},"title":null,"mute":false},{"id":11461716,"updated_at":1452836364,"created_at":1452836364,"content":{"id":"fake_ma_from_element_11461716","updated_at":1452836364,"created_at":1452836364,"type":"image","image":{"id":2242049,"uuid":219202497760825380,"is_processing":false,"representations":{"512":{"url":"https://d12oemfd9cl6ha.cloudfront.net/i/client_uploads/181019/D8375847-F229-486B-B11D-BA5D7AF4C448.jpg?w=512&h=512&crop_mode=fit&v=2","size":{"width":512,"height":341}},"1024":{"url":"https://d12oemfd9cl6ha.cloudfront.net/i/client_uploads/181019/D8375847-F229-486B-B11D-BA5D7AF4C448.jpg?w=1024&h=1024&crop_mode=fit&v=2","size":{"width":1024,"height":683}},"2048":{"url":"media/8e98295b-168f-4ac9-9fd7-4d760e6d60bd.jpg","size":{"width":2048,"height":1365}}},"zoom":1,"focalpoint":{"x":0.5,"y":0.5},"size":{"width":1024,"height":683},"url":"https://d12oemfd9cl6ha.cloudfront.net/i/client_uploads/181019/D8375847-F229-486B-B11D-BA5D7AF4C448.jpg","preprocessed_url":"https://d12oemfd9cl6ha.cloudfront.net/api2/media/client_uploads/181019/D8375847-F229-486B-B11D-BA5D7AF4C448.jpg","low_res_preview":null}},"layout_type":"grid","grid_size":{"width":6,"height":5},"title":null,"mute":false},{"id":11461717,"updated_at":1452836364,"created_at":1452836364,"content":{"id":"fake_ma_from_element_11461717","updated_at":1452836364,"created_at":1452836364,"type":"image","image":{"id":2242052,"uuid":219202523086251140,"is_processing":false,"representations":{"512":{"url":"https://d12oemfd9cl6ha.cloudfront.net/i/client_uploads/181019/593FA0E4-BAF0-4F07-838C-5E70162CB0F6.jpg?w=512&h=512&crop_mode=fit&v=2","size":{"width":512,"height":341}},"1024":{"url":"https://d12oemfd9cl6ha.cloudfront.net/i/client_uploads/181019/593FA0E4-BAF0-4F07-838C-5E70162CB0F6.jpg?w=1024&h=1024&crop_mode=fit&v=2","size":{"width":1024,"height":683}},"2048":{"url":"media/61fbad01-8372-45f8-acfd-84d62e2e5541.jpg","size":{"width":2048,"height":1365}}},"zoom":1.298606395721436,"focalpoint":{"x":0.4343305194328157,"y":0.5255827805394367},"size":{"width":1024,"height":683},"url":"https://d12oemfd9cl6ha.cloudfront.net/i/client_uploads/181019/593FA0E4-BAF0-4F07-838C-5E70162CB0F6.jpg","preprocessed_url":"https://d12oemfd9cl6ha.cloudfront.net/api2/media/client_uploads/181019/593FA0E4-BAF0-4F07-838C-5E70162CB0F6.jpg","low_res_preview":null}},"layout_type":"grid","grid_size":{"width":6,"height":2},"title":null,"mute":false},{"id":11461718,"updated_at":1452836364,"created_at":1452836364,"content":{"id":"fake_ma_from_element_11461718","updated_at":1452836364,"created_at":1452836364,"type":"text","text":{"id":2502707,"plain_text":"Departing too soon, we rejoin Nunzio for our ride down into Taormina, quickly absorbing his strategic suggestions to make best use of our remaining three and a half hours. He dropped us at the far west end of the Corso Umberto to start off the second half of our day. ","rich_text":"","text_style":"body","modifiers":[],"alignment":"left"}},"layout_type":"block","grid_size":{"width":2,"height":2},"title":null,"mute":false},{"id":11461719,"updated_at":1452836364,"created_at":1452836364,"content":{"id":"fake_ma_from_element_11461719","updated_at":1452836364,"created_at":1452836364,"type":"image","image":{"id":2180209,"uuid":214451418518689300,"is_processing":false,"representations":{"512":{"url":"https://d12oemfd9cl6ha.cloudfront.net/i/client_uploads/181019/1329C333-26C6-48B5-9426-6C4C969AA91E.jpg?w=512&h=512&crop_mode=fit&v=2","size":{"width":341,"height":512}},"1024":{"url":"https://d12oemfd9cl6ha.cloudfront.net/i/client_uploads/181019/1329C333-26C6-48B5-9426-6C4C969AA91E.jpg?w=1024&h=1024&crop_mode=fit&v=2","size":{"width":683,"height":1024}},"2048":{"url":"media/eaf44e1a-f343-447a-be02-b7b898ad022a.jpg","size":{"width":1365,"height":2048}}},"zoom":1,"focalpoint":{"x":0.5,"y":0.5},"size":{"width":683,"height":1024},"url":"https://d12oemfd9cl6ha.cloudfront.net/i/client_uploads/181019/1329C333-26C6-48B5-9426-6C4C969AA91E.jpg","preprocessed_url":"https://d12oemfd9cl6ha.cloudfront.net/api2/media/client_uploads/181019/1329C333-26C6-48B5-9426-6C4C969AA91E.jpg","low_res_preview":null}},"layout_type":"grid","grid_size":{"width":3,"height":6},"title":null,"mute":false},{"id":11461720,"updated_at":1452836364,"created_at":1452836364,"content":{"id":"fake_ma_from_element_11461720","updated_at":1452836364,"created_at":1452836364,"type":"image","image":{"id":2242065,"uuid":219203957684983040,"is_processing":false,"representations":{"512":{"url":"https://d12oemfd9cl6ha.cloudfront.net/i/client_uploads/181019/98876A33-C9FA-4D2E-98F0-E9D01FD1A485.jpg?w=512&h=512&crop_mode=fit&v=2","size":{"width":512,"height":341}},"1024":{"url":"https://d12oemfd9cl6ha.cloudfront.net/i/client_uploads/181019/98876A33-C9FA-4D2E-98F0-E9D01FD1A485.jpg?w=1024&h=1024&crop_mode=fit&v=2","size":{"width":1024,"height":683}},"2048":{"url":"media/b7dd1f11-7f65-4492-81e7-3697d5199a5b.jpg","size":{"width":2048,"height":1365}}},"zoom":1,"focalpoint":{"x":0.5,"y":0.5},"size":{"width":1024,"height":683},"url":"https://d12oemfd9cl6ha.cloudfront.net/i/client_uploads/181019/98876A33-C9FA-4D2E-98F0-E9D01FD1A485.jpg","preprocessed_url":"https://d12oemfd9cl6ha.cloudfront.net/api2/media/client_uploads/181019/98876A33-C9FA-4D2E-98F0-E9D01FD1A485.jpg","low_res_preview":null}},"layout_type":"grid","grid_size":{"width":3,"height":3},"title":null,"mute":false},{"id":11461721,"updated_at":1452836364,"created_at":1452836364,"content":{"id":"fake_ma_from_element_11461721","updated_at":1452836364,"created_at":1452836364,"type":"image","image":{"id":2180213,"uuid":214451454642280030,"is_processing":false,"representations":{"512":{"url":"https://d12oemfd9cl6ha.cloudfront.net/i/client_uploads/181019/733C6CB8-7F52-4E4E-AE02-77A0A0592D4F.jpg?w=512&h=512&crop_mode=fit&v=2","size":{"width":512,"height":341}},"1024":{"url":"https://d12oemfd9cl6ha.cloudfront.net/i/client_uploads/181019/733C6CB8-7F52-4E4E-AE02-77A0A0592D4F.jpg?w=1024&h=1024&crop_mode=fit&v=2","size":{"width":1024,"height":683}},"2048":{"url":"media/19a97b34-8ce2-4216-b564-6d70503919d4.jpg","size":{"width":2048,"height":1365}}},"zoom":1,"focalpoint":{"x":0.5,"y":0.5},"size":{"width":1024,"height":683},"url":"https://d12oemfd9cl6ha.cloudfront.net/i/client_uploads/181019/733C6CB8-7F52-4E4E-AE02-77A0A0592D4F.jpg","preprocessed_url":"https://d12oemfd9cl6ha.cloudfront.net/api2/media/client_uploads/181019/733C6CB8-7F52-4E4E-AE02-77A0A0592D4F.jpg","low_res_preview":null}},"layout_type":"grid","grid_size":{"width":3,"height":3},"title":null,"mute":false}],"user":{"updated_at":1444500091,"cached_at":1466282770,"id":181019,"profile_url":"https://www.storehouse.co/me2earth","username":"me2earth","full_name":"Mark Elster","disabled":false,"private":false,"bio":"","instagram_username":"","website":"","authored_channel_id":723396,"favorites_channel_id":723398,"reposts_channel_id":1008854,"hidden_followers":false,"allow_invites_from_strangers":true,"avatar_image":{"id":1275710,"uuid":123473368000815060,"is_processing":false,"representations":{"120":{"url":"https://d12oemfd9cl6ha.cloudfront.net/i/images/imgs/123473368000815055/original.jpeg?w=120&h=120&crop_mode=fit&v=2","size":{"width":120,"height":120}},"320":{"url":"media/5c694047-5722-438b-8b1f-05219e10f792.jpeg","size":{"width":200,"height":200}}},"zoom":1,"focalpoint":{"x":0.5,"y":0.5},"size":{"width":200,"height":200},"url":"https://d12oemfd9cl6ha.cloudfront.net/i/images/imgs/123473368000815055/original.jpeg","preprocessed_url":null,"low_res_preview":null},"cover_image":{"id":1325676,"uuid":128572224714232600,"is_processing":false,"representations":{"512":{"url":"https://d12oemfd9cl6ha.cloudfront.net/i/images/imgs/128572224714232612/original.jpg?w=512&h=512&crop_mode=fit&v=2","size":{"width":384,"height":256}},"1024":{"url":"https://d12oemfd9cl6ha.cloudfront.net/i/images/imgs/128572224714232612/original.jpg?w=1024&h=1024&crop_mode=fit&v=2","size":{"width":384,"height":256}},"2048":{"url":"media/3aae4180-6bea-47d9-9063-946314f4c6bc.jpg","size":{"width":384,"height":256}}},"zoom":1,"focalpoint":{"x":0.5,"y":0.5},"size":{"width":384,"height":256},"url":"https://d12oemfd9cl6ha.cloudfront.net/i/images/imgs/128572224714232612/original.jpg","preprocessed_url":null,"low_res_preview":null},"linked_accounts":[{"id":13795,"service":"facebook","profile_url":"https://www.facebook.com/Me2earth","description":"Mark Elster"}],"following_count":1,"follower_count":3,"stories_count":0,"favorites_count":5,"reposts_count":0,"followed_by_current_user":false},"channels":[],"view_count":31,"sort_time":1413091366,"favorited_by_current_user":false,"reposted_by_current_user":false,"comment_count":0,"blurb":null}